datatransformation/__init__.py
datatransformation/convolution.py
datatransformation/transpose.py
datatransformation/window.py
datatransformation-0.1.1.dist-info/LICENSE
datatransformation-0.1.1.dist-info/METADATA
datatransformation-0.1.1.dist-info/WHEEL
datatransformation-0.1.1.dist-info/RECORD
