Metadata-Version: 2.1
Name: DataTransformation
Version: 0.1.1
Summary: A package for common data science operations
License: MIT
Author: Blessing Agadagba
Author-email: agadagbablessing@gmail.com
Requires-Python: >=3.9,<4.0
Classifier: License :: OSI Approved :: MIT License
Classifier: Programming Language :: Python :: 3
Classifier: Programming Language :: Python :: 3.9
Classifier: Programming Language :: Python :: 3.10
Classifier: Programming Language :: Python :: 3.11
Classifier: Programming Language :: Python :: 3.12
Requires-Dist: numpy (>=1.26.4,<2.0.0)
